allitservice_stubber/__init__.py
allitservice_stubber-0.0.1.dist-info/METADATA
allitservice_stubber-0.0.1.dist-info/WHEEL
allitservice_stubber-0.0.1.dist-info/top_level.txt
allitservice_stubber-0.0.1.dist-info/RECORD
