Metadata-Version: 2.4
Name: allitservice_stubber
Version: 0.0.1
Summary: Stub module that prints an ALL IT Service greeting
Author: ALL IT Service
License: MIT
Project-URL: Homepage, https://allitservice.com
Project-URL: Repository, https://github.com/Blancberg/allitservice-stub
Requires-Python: >=3.8
